fiduswriter/ojs/__init__.py
fiduswriter/ojs/admin.py
fiduswriter/ojs/apps.py
fiduswriter/ojs/constants.py
fiduswriter/ojs/helpers.py
fiduswriter/ojs/models.py
fiduswriter/ojs/token.py
fiduswriter/ojs/urls.py
fiduswriter/ojs/views.py
fiduswriter/ojs/locale/BASE/LC_MESSAGES/django.po
fiduswriter/ojs/locale/bg/LC_MESSAGES/django.mo
fiduswriter/ojs/locale/bg/LC_MESSAGES/django.po
fiduswriter/ojs/locale/bg/LC_MESSAGES/djangojs.mo
fiduswriter/ojs/locale/bg/LC_MESSAGES/djangojs.po
fiduswriter/ojs/locale/de/LC_MESSAGES/django.mo
fiduswriter/ojs/locale/de/LC_MESSAGES/django.po
fiduswriter/ojs/locale/de/LC_MESSAGES/djangojs.mo
fiduswriter/ojs/locale/de/LC_MESSAGES/djangojs.po
fiduswriter/ojs/locale/es/LC_MESSAGES/django.mo
fiduswriter/ojs/locale/es/LC_MESSAGES/django.po
fiduswriter/ojs/locale/es/LC_MESSAGES/djangojs.mo
fiduswriter/ojs/locale/es/LC_MESSAGES/djangojs.po
fiduswriter/ojs/locale/fr/LC_MESSAGES/django.mo
fiduswriter/ojs/locale/fr/LC_MESSAGES/django.po
fiduswriter/ojs/locale/fr/LC_MESSAGES/djangojs.mo
fiduswriter/ojs/locale/fr/LC_MESSAGES/djangojs.po
fiduswriter/ojs/locale/it/LC_MESSAGES/django.mo
fiduswriter/ojs/locale/it/LC_MESSAGES/django.po
fiduswriter/ojs/locale/it/LC_MESSAGES/djangojs.mo
fiduswriter/ojs/locale/it/LC_MESSAGES/djangojs.po
fiduswriter/ojs/locale/pt_BR/LC_MESSAGES/django.mo
fiduswriter/ojs/locale/pt_BR/LC_MESSAGES/django.po
fiduswriter/ojs/locale/pt_BR/LC_MESSAGES/djangojs.mo
fiduswriter/ojs/locale/pt_BR/LC_MESSAGES/djangojs.po
fiduswriter/ojs/migrations/0001_initial.py
fiduswriter/ojs/migrations/0002_remove_submission_file_object.py
fiduswriter/ojs/migrations/0003_journal_templates.py
fiduswriter/ojs/migrations/0004_add_editor.py
fiduswriter/ojs/migrations/0005_submission_authors.py
fiduswriter/ojs/migrations/0006_contributors_replaces_authors.py
fiduswriter/ojs/migrations/0007_move_contributors_from_submission_to_revision.py
fiduswriter/ojs/migrations/0008_reviewer_method.py
fiduswriter/ojs/migrations/__init__.py
fiduswriter_ojs-4.0.0.dist-info/licenses/LICENSE
fiduswriter_ojs-4.0.0.dist-info/METADATA
fiduswriter_ojs-4.0.0.dist-info/WHEEL
fiduswriter_ojs-4.0.0.dist-info/top_level.txt
fiduswriter_ojs-4.0.0.dist-info/RECORD
