Metadata-Version: 2.4
Name: fiduswriter-ojs
Version: 4.0.0
Summary: A Fidus Writer plugin to connect to OJS.
Author-email: Johannes Wilm <johannes@fiduswriter.org>
License: AGPL-3.0-or-later
Project-URL: homepage, https://www.fiduswriter.org/ojs-integration/
Project-URL: repository, https://github.com/fiduswriter/fiduswriter-ojs/
Classifier: Environment :: Web Environment
Classifier: Framework :: Django
Classifier: Framework :: Django :: 5.1
Classifier: Intended Audience :: Developers
Classifier: License :: OSI Approved :: GNU Affero General Public License v3
Classifier: Operating System :: OS Independent
Classifier: Programming Language :: Python
Classifier: Programming Language :: Python :: 3
Classifier: Topic :: Internet :: WWW/HTTP
Classifier: Topic :: Internet :: WWW/HTTP :: Dynamic Content
License-File: LICENSE
Requires-Dist: tenacity==8.2.2
Dynamic: license-file
